propy/AAComposition.py
propy/AAIndex.py
propy/Autocorrelation.py
propy/CTD.py
propy/GetProteinFromUniprot.py
propy/GetSubSeq.py
propy/ProCheck.py
propy/PseudoAAC.py
propy/PyPro.py
propy/QuasiSequenceOrder.py
propy/__init__.py
propy/aaindex/Fig.4.GIF
propy/aaindex/Fig.5-1.GIF
propy/aaindex/Fig.5-2.GIF
propy/aaindex/README.md
propy/aaindex/aaindex1
propy/aaindex/aaindex2
propy/aaindex/aaindex3
propy/data/AvFlexibility.json
propy/data/FreeEnergy.json
propy/data/Mutability.json
propy/data/Polarizability.json
propy/data/README.md
propy/data/ResidueASA.json
propy/data/ResidueVol.json
propy/data/Steric.json
propy/data/grantham-chemical-distance-matrix.json
propy/data/hydrophilicity.json
propy/data/hydrophobicity-autocorrelation.json
propy/data/hydrophobicity.json
propy/data/pI.json
propy/data/pK1.json
propy/data/pK2.json
propy/data/residuemass.json
propy/data/schneider-wrede-physicochemical-distance-matrix.json
propy/data/target.txt
propy3-1.1.1.dist-info/LICENSE
propy3-1.1.1.dist-info/METADATA
propy3-1.1.1.dist-info/WHEEL
propy3-1.1.1.dist-info/top_level.txt
propy3-1.1.1.dist-info/RECORD
