Metadata-Version: 2.1
Name: propy3
Version: 1.1.1
Summary: Compute protein descriptors
Home-page: https://github.com/MartinThoma/propy3
Author: Martin Thoma, Julian Hahnfeld
Author-email: info@martin-thoma.de
Maintainer: Martin Thoma
Maintainer-email: info@martin-thoma.de
License: GPLv2
Keywords: Bio-Informatics,Protein
Platform: UNKNOWN
Classifier: License :: OSI Approved :: GNU General Public License v2 (GPLv2)
Classifier: Programming Language :: Python :: 3
Classifier: Programming Language :: Python :: 3.7
Classifier: Programming Language :: Python :: 3.8
Classifier: Programming Language :: Python :: 3.9
Classifier: Programming Language :: Python :: 3.10
Classifier: Topic :: Scientific/Engineering :: Bio-Informatics
License-File: LICENSE
